{
  "slug": "cheetah-elite-108",
  "title": "高中科學班入學考\n FA00數學系列之靈魂拷問（二）",
  "date": "2024-07-29",
  "category": "學生成果文章",
  "categorySlug": "",
  "bucket": "獵豹菁英",
  "summary": "鋼鐵是如何煉成的～從good到excellent\n 台灣之光!",
  "excerpt": "鋼鐵是如何煉成的～從good到excellent\n 台灣之光!",
  "sourceUrl": "https://www.cheetahstem.com/autopage_detail/1/108",
  "coverImage": "pic/elite/cheetah-elite-108-cover.jpg",
  "imageUrl": "https://www.cheetahstem.com/upload/autopage/20240729170631g0prw.jpg",
  "imageName": "許庭誠.jpg",
  "tags": [
    "學生成果文章",
    "獵豹菁英",
    "2024"
  ],
  "keywords": [],
  "keep": "保留",
  "targetPage": "students.html",
  "bodyHtml": "<div class=\"is-container-in\">\n<div class=\"remote-row clearfix\">\n<div class=\"column full\">\n<h1 class=\"size-64 is-title1-64 is-title-bold\"><span style=\"font-size:48px;\">高中科學班入學考 FA00數學系列之靈魂拷問（二）</span></h1>\n</div>\n</div>\n\n<div class=\"remote-row clearfix\">\n<div class=\"column full\">\n<p class=\"normal-txt\"><span style=\"font-size:24px;\"><a rel=\"noopener noreferrer\" target=\"_blank\" href=\"https://www.facebook.com/groups/695697124716309/posts/1445635029722511/\" role=\"link\" tabindex=\"0\" title=\"\"><span style=\"color:#3498db;\">https://www.facebook.com/groups/695697124716309/permalink/1445635029722511/</span></a><br />\n---<br />\n鋼鐵是如何煉成的～從good到excellent<br />\n台灣之光!<br />\n建中科學班 10年級 許庭誠同學<br />\n以全台第一 超高總分290!!<br />\n（AMC12 150+AIME 140)<br />\n晉級 <span style=\"color:#e74c3c;\">美國數學奧林匹克</span>（USAMO)<br />\nPS:AMC12 150(滿分）<br />\nAIME 140（15題 答對14題）<br />\n<br />\n庭誠同學七年級AMC8 滿分。<br />\n高一拿到北市數學競賽一等獎。<br />\n庭誠不但數學科優異，<br />\n物理 生物 都通過奧賽初選 ！<br />\n而且在建中一年級上學期因數學校隊公假都沒進班上課，只參加考試，學期總成績校排仍維持全校第三（3/970）！<br />\n像許庭誠這類的孩子都會經歷一種脫胎式的成長。<br />\n他們有超乎常人的耐受力與挑戰困難的野心。<br />\n當他們看到傑出的同儕、學長、更大的世界後，會經歷一段掙扎 ，最後脫繭而出 一飛沖天。<br />\n這些成就非凡的孩子，從good到excellent 的過程通常有三個關鍵因素：<br />\n<span style=\"color:#2980b9;\">痛苦煎熬的掙扎<br />\n優秀同儕的激勵<br />\n優秀老師的啟蒙</span><br />\n---</span><br />\n<span style=\"font-size:24px;\">詳情請見下方連結:<br />\n<a rel=\"noopener noreferrer\" target=\"_blank\" href=\"https://www.facebook.com/groups/695697124716309/permalink/1451936802425667/\" title=\"\"><span style=\"color:#3498db;\">https://www.facebook.com/groups/695697124716309/permalink/1451936802425667/</span></a></span></p>\n</div>\n</div>\n</div>",
  "notes": "來源列表頁:\n https://www.cheetahstem.com/autopage/1/all/1",
  "migrationPage": "1",
  "listDescription": "",
  "legacyId": 0,
  "legacyCategoryId": 0,
  "legacyCategoryUrl": "",
  "coverLabel": "",
  "popularity": 0,
  "freshness": 0
}
