{
  "slug": "cheetah-elite-114",
  "title": "獵豹才能超越獵豹!\n 我們締造了難以置信的紀錄!",
  "date": "2024-07-29",
  "category": "學生成果文章",
  "categorySlug": "",
  "bucket": "獵豹菁英",
  "summary": "賀\n 2023 國際國中科奧 台灣六位國手 全獲金牌 獵豹學子 囊括三面! ! !",
  "excerpt": "賀\n 2023 國際國中科奧 台灣六位國手 全獲金牌 獵豹學子 囊括三面! ! !",
  "sourceUrl": "https://www.cheetahstem.com/autopage_detail/1/114",
  "coverImage": "pic/elite/cheetah-elite-114-cover.jpg",
  "imageUrl": "https://www.cheetahstem.com/upload/autopage/20240729174848t8oq6.jpg",
  "imageName": "IJSO.jpg",
  "tags": [
    "學生成果文章",
    "獵豹菁英",
    "2024"
  ],
  "keywords": [],
  "keep": "保留",
  "targetPage": "students.html",
  "bodyHtml": "<div class=\"is-container-in\">\n<div class=\"remote-row clearfix\">\n<div class=\"column full\">\n<h1 class=\"size-64 is-title1-64 is-title-bold\"><span style=\"font-size:48px;\">獵豹才能超越獵豹! 我們締造了難以置信的紀錄!</span></h1>\n</div>\n</div>\n\n<div class=\"remote-row clearfix\">\n<div class=\"column full\">\n<p class=\"normal-txt\"><span style=\"font-size:24px;\">賀<span style=\"color:#e74c3c;\">2023 國際國中科奧</span><br />\n台灣六位國手 全獲金牌<br />\n獵豹學子 囊括三面!!!<br />\n<br />\n天下英才 半數盡出獵豹<br />\n*詹緯濬(參與課程: <span style=\"background-color:#dddddd;\">高中資優數學S系列,AMC,AIME,高階競賽FA</span>)<br />\n*賴敬宇(參與課程: <span style=\"background-color:#dddddd;\">獵豹*寰宇 國中資優數學GM</span>)<br />\n*蘇程玹(參與課程: <span style=\"background-color:#dddddd;\">高中資優數學S系列</span>)<br />\n---<br />\n<br />\n**兩場PK直播反響熱烈,需要回放請按讚留言+1<br />\n主題:<br />\n1.課內學習好的孩子都應超修嗎？【 超修不只是先修】<br />\n2.小學生應參與數學競賽嗎？【 對日後升學的影響/國中數理資優鑑定/私中入學】<br />\n3.小學時期的優秀 能延續下去嗎? 【小時了了 大未必佳的魔咒】<br />\n4.為何獵豹建議低年級的孩子應以閱讀/體能/玩樂為主? 【有些事做了比不做更糟】<br />\n5.什麼是「好的」啟蒙教育?【 PK的教學理念與課程設計】<br />\n6.何謂快樂學習?【快樂意味著沒有困難與挫折嗎? 】<br />\n7.學習時間不夠分配!?【取捨與安排】<br />\n8.只有自律性高的資優生才適合獵豹嗎?【「資優」與「自律」可以培養嗎? 】<br />\n---<br />\n詳情請見下方臉書連結:<br />\n<a rel=\"noopener noreferrer\" target=\"_blank\" href=\"https://www.facebook.com/groups/695697124716309/permalink/1400199770932704/\" title=\"\"><span style=\"color:#3498db;\">https://www.facebook.com/groups/695697124716309/permalink/1400199770932704/</span></a></span></p>\n</div>\n</div>\n</div>",
  "notes": "來源列表頁:\n https://www.cheetahstem.com/autopage/1/all/1",
  "migrationPage": "1",
  "listDescription": "",
  "legacyId": 0,
  "legacyCategoryId": 0,
  "legacyCategoryUrl": "",
  "coverLabel": "",
  "popularity": 0,
  "freshness": 0
}
