{
  "slug": "cheetah-elite-29",
  "title": "筠傑同學\n 獵豹學習心得分享",
  "date": "2023-06-23",
  "category": "學生故事文章",
  "categorySlug": "",
  "bucket": "獵豹菁英",
  "summary": "復興私中\n 九年級 校排一 蘇筠傑同學 學習心得 為了追求卓越而選擇獵豹 而勇氣與毅力成就了卓越！",
  "excerpt": "復興私中\n 九年級 校排一 蘇筠傑同學 學習心得 為了追求卓越而選擇獵豹 而勇氣與毅力成就了卓越！",
  "sourceUrl": "https://www.cheetahstem.com/autopage_detail/1/29",
  "coverImage": "pic/elite/cheetah-elite-29-cover.jpg",
  "imageUrl": "https://www.cheetahstem.com/upload/autopage/202307242022334li18.jpg",
  "imageName": "355850854_6698941740124727_1122563753816293026_n.jpg",
  "tags": [
    "學生故事文章",
    "獵豹菁英",
    "2023"
  ],
  "keywords": [],
  "keep": "保留",
  "targetPage": "students.html",
  "bodyHtml": "<div class=\"is-container-in\">\n<div class=\"remote-row clearfix\">\n<div class=\"column full\" data-ms-editor=\"true\" spellcheck=\"false\">\n<h1 class=\"size-48 is-title1-48 is-title-bold\" style=\"font-size: 32px;\">復興私中 九年級 校排一 蘇筠傑同學 學習心得</h1>\n</div>\n</div>\n\n<div class=\"remote-row clearfix\">\n<div class=\"column half\" data-ms-editor=\"true\" spellcheck=\"false\">\n<p class=\"normal-txt\"><span style=\"font-size: 18px;\"></span><span style=\"font-size:20px;\"><strong>為了追求卓越而選擇獵豹</strong></span><br />\n<span style=\"font-size:18px;\"><strong>而勇氣與毅力成就了卓越！～獵豹以這些卓越的孩子為榮</strong></span><span style=\"font-size: 18px;\"><br />\n獵豹學子<br />\n私立復興高級中學 九年級<br />\n校排一 蘇筠傑同學<br />\n參與獵豹課程:AMC10、S102、S111、微積分、GM(獵豹*寰宇)<br />\n<br />\n<strong>校外比賽:</strong><br />\n八年級- TMT10 獲得\"傑出證書\"(前3%)，及跳級生\"菁英證書\" -<br />\n九年級 - AMC10A 獲得\"CERTIFICATE OF DISTINCTION\"-<br />\n九年級 - AMC12B 獲得\"CERTIFICATE OF DISTINCTION\"，及\"CERTIFICATE OF ACHIEVEMENT\" - AMC10及AMC12皆通過2023 AIME I台灣區邀請標準-<br />\n八年級 - WTMC個人銀牌-<br />\n八年級 - JHMC地區個人二等獎，地區團體三等獎-<br />\n八年級 - IMC初賽一等獎，複賽滿分金牌-<br />\n九年級 - WTMC個人金牌-<br />\n九年級 - JHMC全國個人銀牌，全國團體銀牌</span></p>\n</div>\n\n<div class=\"column half\" data-ms-editor=\"true\" spellcheck=\"false\"><img src=\"pic/elite/cheetah-elite-29-body-1.png\" /></div>\n</div>\n</div>",
  "notes": "來源列表頁:\n https://www.cheetahstem.com/autopage/1/all/3",
  "migrationPage": "3",
  "listDescription": "",
  "legacyId": 0,
  "legacyCategoryId": 0,
  "legacyCategoryUrl": "",
  "coverLabel": "",
  "popularity": 0,
  "freshness": 0
}
