{
  "slug": "education-talk-134",
  "title": "宗翰老師好書推薦",
  "date": "2020-12-19",
  "category": "獵豹談教育",
  "categorySlug": "education-talk",
  "bucket": "文章專欄",
  "summary": "此書有別於一般競賽解題書籍 ，它將一位少年天才思維的心路歷程作了詳細的交代 ，這對任何愛好數學的學習者甚至教師都是非常難得的資料！",
  "excerpt": "此書有別於一般競賽解題書籍 ，它將一位少年天才思維的心路歷程作了詳細的交代 ，這對任何愛好數學的學習者甚至教師都是非常難得的資料！",
  "sourceUrl": "https://www.cheetahstem.com/news_detail/134",
  "coverImage": "pic/columns/2023080508304163783.png",
  "imageUrl": "pic/columns/2023080508304163783.png",
  "imageName": "2023080508304163783.png",
  "tags": [
    "文章專欄",
    "獵豹談教育",
    "2020"
  ],
  "keywords": [],
  "keep": "保留",
  "targetPage": "columns.html",
  "bodyHtml": "<div class=\"is-container-in\">\n<div class=\"remote-row clearfix\">\n<div class=\"column half\">\n<p class=\"normal-txt\"><strong><span style=\"font-size:28px;\">宗翰老師好書推薦</span></strong><br />\n<span style=\"font-size:18px;\"></span></p>\n\n<div class=\"edit\"><span style=\"font-size:20px;\"><br />\n<a rel=\"noopener noreferrer\" href=\"https://www.books.com.tw/products/0010509872?fbclid=IwAR0LMuXxZoW6YON4TTSsM8lo1FeYIi98WBTLXWG_8tJUkbFqb6MaC1nBQyA\" target=\"_blank\" title=\"\">https://www.books.com.tw/products/0010509872?fbclid=IwAR0LMuXxZoW6YON4TTSsM8lo1FeYIi98WBTLXWG_8tJUkbFqb6MaC1nBQyA</a></span>\n\n<div>\n<p><span style=\"font-size:20px;\"></span></p>\n\n<div class=\"edit\">\n<div class=\"edit\">\n<p class=\"normal-txt\"><span style=\"font-size:20px;\"></span></p>\n</div>\n</div>\n\n<p><span style=\"font-size:20px;\"><a rel=\"noopener noreferrer\" href=\"https://www.facebook.com/groups/695697124716309/permalink/718141199138568/?mibextid=lURqYx\" target=\"_blank\" title=\"\">&nbsp;https://www.facebook.com/groups/695697124716309/permalink/718141199138568/?mibextid=lURqYx</a></span></p>\n</div>\n</div>\n\n<p>&nbsp;</p>\n</div>\n\n<div class=\"column half\"><img src=\"pic/columns/2023080508304163783-62200dc7.png\" /></div>\n</div>\n</div>",
  "notes": "舊站自動搬移於 2026-03-24",
  "migrationPage": "news/education-talk",
  "listDescription": "此書有別於一般競賽解題書籍 ，它將一位少年天才思維的心路歷程作了詳細的交代 ，這對任何愛好數學的學習者甚至教師都是非常難得的資料！",
  "legacyId": 134,
  "legacyCategoryId": 9,
  "legacyCategoryUrl": "https://www.cheetahstem.com/news/9/1",
  "coverLabel": "",
  "popularity": 0,
  "freshness": 0
}
